{
  "title": "✍️ Xem lại đề viết mã số 74 - Part 1",
  "question": "You should spend about 20 minutes on this task.\n\nYou have just received an email from your English pen-friend, Peter, accepting your invitation to come and stay with you for the New Year celebration. Read part of his letter below.\nThanks very much for the invitation to stay with you and your family for a few days during Christmas - of course, I'd love to come!\nI've already booked my flights, and I will be arriving at 2:30 pm on the 22nd of December. As you know, I've never been abroad during the Christmas holidays, so I have no idea what to do.\nWhat's the weather like there at that time of year? What kinds of clothes should I bring? Anyway, what kinds of gifts are good for a first-time meeting with your family?\nWrite an email responding to him.\nYou should write at least 120 words. Do not include your name. Your response will be evaluated in terms of Task Fulfillment, Organization, Vocabulary and Grammar.",
  "translation": "Bạn nên dành khoảng 20 phút cho nhiệm vụ này.\n\nBạn vừa nhận được một email từ Peter, một người bạn thân qua thư người Anh, xác nhận lời mời của bạn đến chơi và đón năm mới cùng gia đình bạn. Hãy đọc một phần lá thư của anh ấy dưới đây.\nCảm ơn bạn rất nhiều vì đã mời mình đến ở cùng bạn và gia đình trong vài ngày vào dịp Giáng sinh - tất nhiên là mình rất muốn đến!\nMình đã đặt vé máy bay rồi, và mình sẽ đến vào lúc 2:30 chiều ngày 22 tháng 12. Như bạn biết đấy, mình chưa bao giờ ra nước ngoài vào dịp Giáng sinh, vì vậy mình không biết nên làm gì.\nThời tiết vào thời điểm đó ở chỗ bạn như thế nào? Mình nên mang theo những loại quần áo gì? À, nhân tiện, mình nên mang theo món quà nào để tặng gia đình bạn trong lần gặp đầu tiên?\nHãy viết một email trả lời Peter.\nBạn nên viết ít nhất 120 từ. Không bao gồm tên của bạn. Bài viết của bạn sẽ được đánh giá dựa trên các tiêu chí Mức độ hoàn thành, Tổ chức bài viết, Từ vựng và Ngữ pháp.",
  "test_id": 74,
  "results_url": "https://luyenthivstep.vn/luyen-de/ket-qua-viet/153223"
}