{
  "title": "✍️ Xem lại đề nói mã số 160 - Part 1",
  "question": "Let's talk about a room in your house.\n- What is your favorite room in your house?\n- What do you usually do in your room?\n- How do you like to decorate your room?\nNow, let's talk about secondary school.\n- Who is your favorite teacher at secondary school?\n- What is your favorite subject?\n- What subject do you find the most difficult?\n🎤 Bài thu âm của bạn:\nTrình duyệt của bạn không hỗ trợ phát audio.\n🎫 Bạn còn\n0\nlượt chấm  | \n\t\t\t\t\t\t🧾 Cần\n0.5\nlượt để gửi yêu cầu chấm bài này.\n⚠️ Bạn không đủ lượt chấm để yêu cầu.\nBạn cần tối thiểu 0.5 lượt chấm.\n💳 Nạp thêm lượt chấm\n🚀 Tiếp tục luyện đề\n📜 Lịch sử làm bài",
  "translation": "Hãy nói về một căn phòng trong nhà bạn.\n- Phòng bạn thích nhất trong nhà là gì?\n- Bạn thường làm gì trong phòng đó?\n- Bạn thích trang trí phòng mình như thế nào?\nBây giờ, hãy nói về trường trung học.\n- Ai là giáo viên bạn thích nhất ở trường trung học?\n- Môn học bạn yêu thích nhất là gì?\n- Môn học nào bạn thấy khó nhất?",
  "test_id": 160,
  "results_url": "https://luyenthivstep.vn/luyen-de/ket-qua-noi/167768"
}